google_flights_mcp/__init__.py
google_flights_mcp/airport_data.py
google_flights_mcp/cli.py
google_flights_mcp/models.py
google_flights_mcp/server.py
google_flights_mcp-0.1.0.dist-info/METADATA
google_flights_mcp-0.1.0.dist-info/WHEEL
google_flights_mcp-0.1.0.dist-info/entry_points.txt
google_flights_mcp-0.1.0.dist-info/licenses/LICENSE
google_flights_mcp-0.1.0.dist-info/RECORD
