Metadata-Version: 2.4
Name: google-flights-mcp
Version: 0.1.0
Summary: A FastMCP server for accessing Google Flights data via Model Context Protocol
Project-URL: Homepage, https://github.com/tistaharahap/google-flights-mcp
Project-URL: Repository, https://github.com/tistaharahap/google-flights-mcp
Project-URL: Documentation, https://github.com/tistaharahap/google-flights-mcp#readme
Project-URL: Issues, https://github.com/tistaharahap/google-flights-mcp/issues
Author-email: Batista Harahap <batista@bango29.com>
License: MIT
License-File: LICENSE
Keywords: fastmcp,flight-search,google-flights,mcp,model-context-protocol
Classifier: Development Status :: 4 - Beta
Classifier: Intended Audience :: Developers
Classifier: License :: OSI Approved :: MIT License
Classifier: Operating System :: OS Independent
Classifier: Programming Language :: Python :: 3
Classifier: Programming Language :: Python :: 3.8
Classifier: Programming Language :: Python :: 3.9
Classifier: Programming Language :: Python :: 3.10
Classifier: Programming Language :: Python :: 3.11
Classifier: Programming Language :: Python :: 3.12
Classifier: Programming Language :: Python :: 3.13
Classifier: Topic :: Internet :: WWW/HTTP :: Indexing/Search
Classifier: Topic :: Software Development :: Libraries :: Python Modules
Requires-Python: >=3.8
Requires-Dist: fast-flights>=2.2
Requires-Dist: fastmcp>=2.12.3
Requires-Dist: rich>=14.1.0
Requires-Dist: typer>=0.17.4
